LICENSE
jsomark/__init__.py
jsomark/api.py
jsomark/composer.py
jsomark-0.2.2.dist-info/LICENSE
jsomark-0.2.2.dist-info/WHEEL
jsomark-0.2.2.dist-info/METADATA
jsomark-0.2.2.dist-info/RECORD
