Metadata-Version: 2.1
Name: jsomark
Version: 0.2.2
Summary: json to xml composing and parsing convention.
Home-page: https://github.com/knowark/jsomark
License: MIT
Keywords: json,xml
Author: Knowark
Requires-Python: >=3.6,<4.0
Classifier: License :: OSI Approved :: MIT License
Classifier: Programming Language :: Python :: 3
Classifier: Programming Language :: Python :: 3.6
Classifier: Programming Language :: Python :: 3.7
Classifier: Programming Language :: Python :: 3.8
Requires-Dist: lxml (>=4.5.0,<5.0.0)
Requires-Dist: pytest (>=5.3.5,<6.0.0)
Project-URL: Repository, https://github.com/knowark/jsomark
